scmcc/__init__.py
scmcc-0.0.1.dist-info/METADATA
scmcc-0.0.1.dist-info/WHEEL
scmcc-0.0.1.dist-info/top_level.txt
scmcc-0.0.1.dist-info/RECORD
