Metadata-Version: 2.4
Name: scmcc
Version: 0.0.1
Summary: SCMCC
Author-email: Your Name <your.email@example.com>
Classifier: Development Status :: 1 - Planning
Classifier: Programming Language :: Python :: 3
Requires-Python: >=3.7
